selenium_form_killer/__init__.py
selenium_form_killer/anti_captcha/__init__.py
selenium_form_killer/anti_captcha/anti_captcha.py
selenium_form_killer/capmonster/__init__.py
selenium_form_killer/capmonster/captcha_breaker.py
selenium_form_killer/forms.py
selenium_form_killer/killer.py
selenium_form_killer/log/logger.py
selenium_form_killer/types/generic_types.py
selenium_form_killer/types/selenium_types.py
selenium_form_killer/util/__init__.py
selenium_form_killer/util/util.py
selenium_form_killer-0.1.11.dist-info/METADATA
selenium_form_killer-0.1.11.dist-info/WHEEL
selenium_form_killer-0.1.11.dist-info/RECORD
