Metadata-Version: 2.1
Name: selenium-form-killer
Version: 0.1.11
Summary: 
License: MIT
Author: Rodrigoneal
Author-email: rodrigho2006@gmail.com
Requires-Python: >=3.9,<4.0
Classifier: License :: OSI Approved :: MIT License
Classifier: Programming Language :: Python :: 3
Classifier: Programming Language :: Python :: 3.9
Classifier: Programming Language :: Python :: 3.10
Classifier: Programming Language :: Python :: 3.11
Classifier: Programming Language :: Python :: 3.12
Requires-Dist: bs4 (>=0.0.2,<0.0.3)
Requires-Dist: capmonstercloudclient (>=1.3.4,<2.0.0)
Requires-Dist: chardet (>=5.2.0,<6.0.0)
Requires-Dist: coverage (>=7.5.0,<8.0.0)
Requires-Dist: httpx (>=0.27.0,<0.28.0)
Requires-Dist: loguru (>=0.7.2,<0.8.0)
Requires-Dist: mypy (>=1.10.0,<2.0.0)
Requires-Dist: playwright (>=1.43.0,<2.0.0)
Requires-Dist: pytest-asyncio (>=0.23.5,<0.24.0)
Requires-Dist: python-dotenv (>=1.0.1,<2.0.0)
Requires-Dist: requests (>=2.31.0,<3.0.0)
Requires-Dist: respx (>=0.21.1,<0.22.0)
Requires-Dist: typing-extensions (>=4.9.0,<5.0.0)
